{
    "timestamp_utc": "2026-03-04T05:00:00+00:00",
    "hour": 7,
    "hour_formatted": "07:00",
    "city": "paris",
    "station_id": 5722,
    "station_name": "Paris",
    "station_coordinates": {
        "lat": 48.856614,
        "lon": 2.3522219
    },
    "station_url": "https://aqicn.org/city/paris",
    "aqi": 68,
    "alert_level": "moderate",
    "aqi_category": "moderate",
    "dominant_pollutant_api": "pm25",
    "pm25": 68,
    "pm10": 21,
    "no2": 36.4,
    "o3": 3.1,
    "co": 0.1,
    "so2": 0.6,
    "no": null,
    "nh3": null,
    "primary_pollutant": "pm25",
    "pm25_to_pm10_ratio": 3.24,
    "no2_to_o3_ratio": 11.74,
    "temperature_celsius": 7.7,
    "humidity_percent": 87.7,
    "pressure_hpa": 1025.8,
    "wind_speed_mps": 0.2,
    "wind_gust_mps": null,
    "dew_point_celsius": null,
    "health_risk": {
        "score": 13.6,
        "level": "moderate",
        "outdoor_activity": "safe",
        "sensitive_groups": "caution",
        "mask_recommended": false
    },
    "uvi_forecast_daily": [
        {
            "date": "2026-03-03",
            "avg": 0,
            "min": 0,
            "max": 2
        },
        {
            "date": "2026-03-04",
            "avg": 0,
            "min": 0,
            "max": 2
        },
        {
            "date": "2026-03-05",
            "avg": 0,
            "min": 0,
            "max": 2
        },
        {
            "date": "2026-03-06",
            "avg": 0,
            "min": 0,
            "max": 2
        },
        {
            "date": "2026-03-07",
            "avg": 0,
            "min": 0,
            "max": 2
        },
        {
            "date": "2026-03-08",
            "avg": 1,
            "min": 0,
            "max": 2
        }
    ],
    "station_timezone": "+01:00",
    "attributions": [
        "AirParif - Association de surveillance de la qualit\u00c3\u00a9 de l'air en \u00c3\u017dle-de-France",
        "European Environment Agency",
        "World Air Quality Index Project"
    ],
    "_data_quality": {
        "completeness_score": 0.75,
        "available_pollutants": 6,
        "total_pollutants": 8
    },
    "_lineage": {
        "transformer": "AirQualityTransformer",
        "version": "3.0",
        "transformed_at": "2026-03-04T07:51:53.337130+00:00",
        "raw_source": "C:\\Users\\Seif\\Desktop\\weather_etl_v2\\data\\raw\\city=paris\\year=2026\\month=03\\day=04\\air_quality_07_raw.json"
    }
}